LICENSE
MANIFEST.in
README.md
setup.py
canjs/__init__.py
canjs/forms.py
canjs/models.py
canjs/urls.py
canjs/utils.py
canjs/views.py
canjs/static/canjs/csrf.js
canjs/static/canjs/1.0.5/can.construct.proxy.js
canjs/static/canjs/1.0.5/can.construct.super.js
canjs/static/canjs/1.0.5/can.control.plugin.js
canjs/static/canjs/1.0.5/can.control.view.js
canjs/static/canjs/1.0.5/can.dojo.js
canjs/static/canjs/1.0.5/can.dojo.min.js
canjs/static/canjs/1.0.5/can.fixture.js
canjs/static/canjs/1.0.5/can.jquery.js
canjs/static/canjs/1.0.5/can.jquery.min.js
canjs/static/canjs/1.0.5/can.mootools.js
canjs/static/canjs/1.0.5/can.mootools.min.js
canjs/static/canjs/1.0.5/can.observe.attributes.js
canjs/static/canjs/1.0.5/can.observe.backup.js
canjs/static/canjs/1.0.5/can.observe.delegate.js
canjs/static/canjs/1.0.5/can.observe.setter.js
canjs/static/canjs/1.0.5/can.observe.validations.js
canjs/static/canjs/1.0.5/can.view.modifiers.js
canjs/static/canjs/1.0.5/can.yui.js
canjs/static/canjs/1.0.5/can.yui.min.js
canjs/static/canjs/1.0.5/can.zepto.js
canjs/static/canjs/1.0.5/can.zepto.min.js
canjs/static/canjs/1.1.1/can.construct.proxy.js
canjs/static/canjs/1.1.1/can.construct.super.js
canjs/static/canjs/1.1.1/can.control.plugin.js
canjs/static/canjs/1.1.1/can.control.view.js
canjs/static/canjs/1.1.1/can.dojo.js
canjs/static/canjs/1.1.1/can.dojo.min.js
canjs/static/canjs/1.1.1/can.fixture.js
canjs/static/canjs/1.1.1/can.jquery-all.js
canjs/static/canjs/1.1.1/can.jquery-all.min.js
canjs/static/canjs/1.1.1/can.jquery.js
canjs/static/canjs/1.1.1/can.jquery.min.js
canjs/static/canjs/1.1.1/can.mootools.js
canjs/static/canjs/1.1.1/can.mootools.min.js
canjs/static/canjs/1.1.1/can.observe.attributes.js
canjs/static/canjs/1.1.1/can.observe.backup.js
canjs/static/canjs/1.1.1/can.observe.delegate.js
canjs/static/canjs/1.1.1/can.observe.setter.js
canjs/static/canjs/1.1.1/can.observe.validations.js
canjs/static/canjs/1.1.1/can.view.modifiers.js
canjs/static/canjs/1.1.1/can.view.mustache.js
django_canjs.egg-info/PKG-INFO
django_canjs.egg-info/SOURCES.txt
django_canjs.egg-info/dependency_links.txt
django_canjs.egg-info/top_level.txt