Metadata-Version: 1.1
Name: django-canjs
Version: 0.1.2
Summary: CanJS integration library for Django
Home-page: https://github.com/aljosa/django-canjs
Author: Aljosa Mohorovic
Author-email: aljosa.mohorovic@gmail.com
License: MIT License
Keywords: django canjs
Platform: any
Classifier: Development Status :: 2 - Pre-Alpha
Classifier: Environment :: Web Environment
Classifier: Framework :: Django
Classifier: Intended Audience :: Developers
Classifier: License :: OSI Approved :: MIT License
Classifier: Operating System :: OS Independent
Classifier: Programming Language :: Python
Classifier: Topic :: Software Development :: Libraries :: Application Frameworks
Classifier: Topic :: Software Development :: Libraries :: Python Modules
